{
  "annotations": {
    "list": []
  },
  "editable": true,
  "fiscalYearStartMonth": 0,
  "graphTooltip": 0,
  "id": null,
  "links": [],
  "panels": [
    {
      "collapsed": false,
      "gridPos": { "h": 1, "w": 24, "x": 0, "y": 0 },
      "id": 100,
      "title": "🟢 All Logs",
      "type": "row"
    },
    {
      "datasource": { "type": "loki", "uid": "${DS_LOKI}" },
      "gridPos": { "h": 8, "w": 12, "x": 0, "y": 1 },
      "id": 1,
      "options": {
        "dedupStrategy": "none",
        "enableLogDetails": true,
        "prettifyLogMessage": false,
        "showCommonLabels": false,
        "showLabels": false,
        "showTime": true,
        "sortOrder": "Descending",
        "wrapLogMessage": true
      },
      "targets": [
        {
          "datasource": { "type": "loki", "uid": "${DS_LOKI}" },
          "editorMode": "code",
          "expr": "{container=\"dfr-api-server\"}",
          "queryType": "range",
          "refId": "A"
        }
      ],
      "title": "DFR API Server Logs",
      "type": "logs"
    },
    {
      "datasource": { "type": "loki", "uid": "${DS_LOKI}" },
      "gridPos": { "h": 8, "w": 12, "x": 12, "y": 1 },
      "id": 2,
      "options": {
        "dedupStrategy": "none",
        "enableLogDetails": true,
        "prettifyLogMessage": false,
        "showCommonLabels": false,
        "showLabels": false,
        "showTime": true,
        "sortOrder": "Descending",
        "wrapLogMessage": true
      },
      "targets": [
        {
          "datasource": { "type": "loki", "uid": "${DS_LOKI}" },
          "editorMode": "code",
          "expr": "{container=\"vms-api-server\"}",
          "queryType": "range",
          "refId": "A"
        }
      ],
      "title": "VMS API Server Logs",
      "type": "logs"
    },
    {
      "collapsed": false,
      "gridPos": { "h": 1, "w": 24, "x": 0, "y": 9 },
      "id": 200,
      "title": "🔴 Error Logs",
      "type": "row"
    },
    {
      "datasource": { "type": "loki", "uid": "${DS_LOKI}" },
      "gridPos": { "h": 8, "w": 12, "x": 0, "y": 10 },
      "id": 3,
      "options": {
        "dedupStrategy": "none",
        "enableLogDetails": true,
        "prettifyLogMessage": false,
        "showCommonLabels": false,
        "showLabels": false,
        "showTime": true,
        "sortOrder": "Descending",
        "wrapLogMessage": true
      },
      "targets": [
        {
          "datasource": { "type": "loki", "uid": "${DS_LOKI}" },
          "editorMode": "code",
          "expr": "{container=\"dfr-api-server\"} |~ \"(?i)(error|err|fatal|panic|exception|fail|critical)\"",
          "queryType": "range",
          "refId": "A"
        }
      ],
      "title": "⚠️ DFR API Server Error Logs",
      "type": "logs"
    },
    {
      "datasource": { "type": "loki", "uid": "${DS_LOKI}" },
      "gridPos": { "h": 8, "w": 12, "x": 12, "y": 10 },
      "id": 4,
      "options": {
        "dedupStrategy": "none",
        "enableLogDetails": true,
        "prettifyLogMessage": false,
        "showCommonLabels": false,
        "showLabels": false,
        "showTime": true,
        "sortOrder": "Descending",
        "wrapLogMessage": true
      },
      "targets": [
        {
          "datasource": { "type": "loki", "uid": "${DS_LOKI}" },
          "editorMode": "code",
          "expr": "{container=\"vms-api-server\"} |~ \"(?i)(error|err|fatal|panic|exception|fail|critical)\"",
          "queryType": "range",
          "refId": "A"
        }
      ],
      "title": "⚠️ VMS API Server Error Logs",
      "type": "logs"
    }
  ],
  "schemaVersion": 39,
  "tags": ["logs", "loki", "api", "dfr", "vms"],
  "templating": {
    "list": [
      {
        "current": {},
        "hide": 0,
        "includeAll": false,
        "name": "DS_LOKI",
        "query": "loki",
        "type": "datasource"
      }
    ]
  },
  "time": { "from": "now-1h", "to": "now" },
  "timepicker": {},
  "timezone": "browser",
  "title": "API Logs & Errors",
  "uid": "api-logs-errors",
  "version": 1
}
